{"chunk_definitions":[{"row":14,"row_count":1,"visible":true,"expansion_state":0,"options":{"engine":"r","label":"setup","include":false},"document_id":"4C757AE1","chunk_id":"csetup_chunk","chunk_label":"setup"},{"row":32,"row_count":1,"visible":true,"expansion_state":0,"options":{"engine":"r","label":"vis_miss","eval":false},"document_id":"4C757AE1","chunk_id":"cwbmkmo975oe8","chunk_label":"vis_miss"},{"row":45,"row_count":1,"visible":true,"expansion_state":0,"options":{"engine":"r","label":"unnamed-chunk-4"},"document_id":"4C757AE1","chunk_id":"c8flukh3o6xtz","chunk_label":"unnamed-chunk-2"},{"row":53,"row_count":1,"visible":true,"expansion_state":0,"options":{"engine":"r","label":"unnamed-chunk-5"},"document_id":"4C757AE1","chunk_id":"cy8t2ib7ed6no","chunk_label":"unnamed-chunk-3"},{"row":67,"row_count":1,"visible":true,"expansion_state":0,"options":{"engine":"r","label":"unnamed-chunk-6"},"document_id":"4C757AE1","chunk_id":"ch8d8hi0h75i5","chunk_label":"unnamed-chunk-4"},{"row":75,"row_count":1,"visible":true,"expansion_state":0,"options":{"engine":"r","label":"sal_five_num_sum"},"document_id":"4C757AE1","chunk_id":"cehvfu8o57xm6","chunk_label":"sal_five_num_sum"},{"row":95,"row_count":1,"visible":true,"expansion_state":0,"options":{"engine":"r","label":"unnamed-chunk-7"},"document_id":"4C757AE1","chunk_id":"cgpscvfw3nqrx","chunk_label":"unnamed-chunk-5"},{"row":106,"row_count":1,"visible":true,"expansion_state":0,"options":{"engine":"r","label":"unnamed-chunk-8"},"document_id":"4C757AE1","chunk_id":"cy8pcp3qkx03q","chunk_label":"unnamed-chunk-6"},{"row":118,"row_count":1,"visible":true,"expansion_state":0,"options":{"engine":"r","message":false,"warning":false,"label":"unnamed-chunk-9"},"document_id":"4C757AE1","chunk_id":"ckf1rirz8hz08","chunk_label":"unnamed-chunk-7"},{"row":129,"row_count":1,"visible":true,"expansion_state":0,"options":{"engine":"r","label":"unnamed-chunk-10"},"document_id":"4C757AE1","chunk_id":"ca3syd7u2gx1i","chunk_label":"unnamed-chunk-8"},{"row":142,"row_count":1,"visible":true,"expansion_state":0,"options":{"engine":"r","label":"unnamed-chunk-11"},"document_id":"4C757AE1","chunk_id":"cv6ho1zplmqhx","chunk_label":"unnamed-chunk-9"},{"row":162,"row_count":1,"visible":true,"expansion_state":0,"options":{"engine":"r","label":"unnamed-chunk-12"},"document_id":"4C757AE1","chunk_id":"csrgengbnr0w4","chunk_label":"unnamed-chunk-10"},{"row":180,"row_count":1,"visible":true,"expansion_state":0,"options":{"engine":"r","label":"unnamed-chunk-13"},"document_id":"4C757AE1","chunk_id":"cbjp3y0fl5k9f","chunk_label":"unnamed-chunk-11"},{"row":193,"row_count":1,"visible":true,"expansion_state":0,"options":{"engine":"r","label":"unnamed-chunk-14"},"document_id":"4C757AE1","chunk_id":"cvk6ee5qmueyj","chunk_label":"unnamed-chunk-12"},{"row":210,"row_count":1,"visible":true,"expansion_state":0,"options":{"engine":"r","label":"unnamed-chunk-15"},"document_id":"4C757AE1","chunk_id":"czt95i19762dc","chunk_label":"unnamed-chunk-13"},{"row":224,"row_count":1,"visible":true,"expansion_state":0,"options":{"engine":"r","label":"unnamed-chunk-16"},"document_id":"4C757AE1","chunk_id":"csozsvz9uhh8z","chunk_label":"unnamed-chunk-14"},{"row":246,"row_count":1,"visible":true,"expansion_state":0,"options":{"engine":"r","label":"unnamed-chunk-24"},"document_id":"4C757AE1","chunk_id":"cljsbcvrasmsg","chunk_label":"unnamed-chunk-15"},{"row":253,"row_count":1,"visible":true,"expansion_state":0,"options":{"engine":"r","label":"unnamed-chunk-61"},"document_id":"4C757AE1","chunk_id":"cwst55kxanuz2","chunk_label":"unnamed-chunk-16"},{"row":258,"row_count":1,"visible":true,"expansion_state":0,"options":{"engine":"r","label":"unnamed-chunk-62"},"document_id":"4C757AE1","chunk_id":"cx1spl99vojnp","chunk_label":"unnamed-chunk-17"},{"row":280,"row_count":1,"visible":true,"expansion_state":0,"options":{"engine":"r","label":"unnamed-chunk-35"},"document_id":"4C757AE1","chunk_id":"cvixqdgyg3hz7","chunk_label":"unnamed-chunk-18"},{"row":289,"row_count":1,"visible":true,"expansion_state":0,"options":{"engine":"r","label":"unnamed-chunk-36"},"document_id":"4C757AE1","chunk_id":"cz7sl8vbwus9a","chunk_label":"unnamed-chunk-19"}],"doc_write_time":1642393616}